[
  {
    "step": 1,
    "label": "initial_page",
    "filepath": "screenshots/workflow_1762703348246/step_001_initial_page.png",
    "url": "https://github.com/",
    "timestamp": "2025-11-09T15:49:13.465Z",
    "metadata": {
      "task": "creating a new repository in GitHub",
      "step": "initial"
    }
  },
  {
    "step": 2,
    "label": "click_the_sign_in_button_to_pr",
    "filepath": "screenshots/workflow_1762703348246/step_002_click_the_sign_in_button_to_pr.png",
    "url": "https://github.com/login?return_to=https%3A%2F%2Fgithub.com%2Fsignup%3Fsource%3Dform-home-signup%26user_email%3D",
    "timestamp": "2025-11-09T15:49:31.969Z",
    "metadata": {
      "task": "creating a new repository in GitHub",
      "step": 1,
      "action": "click",
      "description": "Click the 'Sign in' button to proceed to the login page."
    }
  },
  {
    "step": 3,
    "label": "enter_a_placeholder_username_o",
    "filepath": "screenshots/workflow_1762703348246/step_003_enter_a_placeholder_username_o.png",
    "url": "https://github.com/login?return_to=https%3A%2F%2Fgithub.com%2Fsignup%3Fsource%3Dform-home-signup%26user_email%3D",
    "timestamp": "2025-11-09T15:49:45.428Z",
    "metadata": {
      "task": "creating a new repository in GitHub",
      "step": 2,
      "action": "fill",
      "description": "Enter a placeholder username or email address to initiate sign in."
    }
  },
  {
    "step": 4,
    "label": "filling_form_fields",
    "filepath": "screenshots/workflow_1762703348246/step_004_filling_form_fields.png",
    "url": "https://github.com/login?return_to=https%3A%2F%2Fgithub.com%2Fsignup%3Fsource%3Dform-home-signup%26user_email%3D",
    "timestamp": "2025-11-09T15:49:54.422Z",
    "metadata": {
      "task": "creating a new repository in GitHub",
      "step": 3,
      "action": "fill",
      "description": "Filling in a placeholder password to sign in."
    }
  },
  {
    "step": 5,
    "label": "click_the_sign_in_button_to_lo",
    "filepath": "screenshots/workflow_1762703348246/step_005_click_the_sign_in_button_to_lo.png",
    "url": "https://github.com/password_reset",
    "timestamp": "2025-11-09T15:51:05.555Z",
    "metadata": {
      "task": "creating a new repository in GitHub",
      "step": 4,
      "action": "click",
      "description": "Click the Sign in button to log into GitHub."
    }
  },
  {
    "step": 6,
    "label": "modal_open",
    "filepath": "screenshots/workflow_1762703348246/step_006_modal_open.png",
    "url": "https://github.com/",
    "timestamp": "2025-11-09T15:51:19.934Z",
    "metadata": {
      "task": "creating a new repository in GitHub",
      "step": 5,
      "action": "navigate",
      "description": "The current page is a password reset page, which prevents creating a repository. Navigating to the GitHub homepage to proceed with sign-in or repository creation."
    }
  }
]
